molecule_hetznercloud/__init__.py
molecule_hetznercloud/_version.py
molecule_hetznercloud/driver.json
molecule_hetznercloud/driver.py
molecule_hetznercloud/cookiecutter/cookiecutter.json
molecule_hetznercloud/cookiecutter/{{cookiecutter.molecule_directory}}/{{cookiecutter.scenario_name}}/INSTALL.rst
molecule_hetznercloud/cookiecutter/{{cookiecutter.molecule_directory}}/{{cookiecutter.scenario_name}}/converge.yml
molecule_hetznercloud/cookiecutter/{{cookiecutter.molecule_directory}}/{{cookiecutter.scenario_name}}/molecule.yml
molecule_hetznercloud/playbooks/create.yml
molecule_hetznercloud/playbooks/destroy.yml
molecule_hetznercloud/playbooks/filter_plugins/get_platforms_data.py
molecule_hetznercloud-2.7.0.dist-info/licenses/LICENSE
molecule_hetznercloud-2.7.0.dist-info/METADATA
molecule_hetznercloud-2.7.0.dist-info/WHEEL
molecule_hetznercloud-2.7.0.dist-info/entry_points.txt
molecule_hetznercloud-2.7.0.dist-info/top_level.txt
molecule_hetznercloud-2.7.0.dist-info/RECORD
