Metadata-Version: 2.4
Name: molecule-hetznercloud
Version: 2.7.0
Summary: Molecule driver for Hetzner Cloud
Home-page: https://github.com/ansible-community/molecule-hetznercloud
Author: Hetzner Cloud GmbH
Author-email: support-cloud@hetzner.com
License: LGPL
Project-URL: Bug Tracker, https://github.com/ansible-community/molecule-hetznercloud/issues
Project-URL: Documentation, https://github.com/ansible-community/molecule-hetznercloud#readme
Project-URL: Changelog, https://github.com/ansible-community/molecule-hetznercloud/blob/main/CHANGELOG.md
Project-URL: Source Code, https://github.com/ansible-community/molecule-hetznercloud
Keywords: ansible molecule driver hcloud hetzner cloud testing
Classifier: Development Status :: 5 - Production/Stable
Classifier: Environment :: Console
Classifier: Intended Audience :: Developers
Classifier: Intended Audience :: Information Technology
Classifier: Intended Audience :: System Administrators
Classifier: License :: OSI Approved :: GNU Lesser General Public License v3 (LGPLv3)
Classifier: Natural Language :: English
Classifier: Operating System :: OS Independent
Classifier: Programming Language :: Python :: 3
Classifier: Programming Language :: Python :: 3.10
Classifier: Programming Language :: Python :: 3.11
Classifier: Programming Language :: Python :: 3.12
Classifier: Programming Language :: Python :: 3.13
Classifier: Topic :: System :: Systems Administration
Classifier: Topic :: Utilities
Requires-Python: >=3.10
License-File: LICENSE
Requires-Dist: molecule>=5.0.0
Requires-Dist: python-dateutil>=2.7.5
Requires-Dist: requests>=2.20
Requires-Dist: netaddr
Provides-Extra: test
Requires-Dist: tox<5.0,>=4.11.3; extra == "test"
Requires-Dist: pytest-xdist<4.0,>=3.3.1; extra == "test"
Requires-Dist: pytest<9.1,>=9; extra == "test"
Requires-Dist: pytest-ansible<25.13,>=25.12; extra == "test"
Requires-Dist: pytest-cov<7.1,>=7; extra == "test"
Dynamic: author
Dynamic: author-email
Dynamic: classifier
Dynamic: description
Dynamic: description-content-type
Dynamic: home-page
Dynamic: keywords
Dynamic: license
Dynamic: license-file
Dynamic: project-url
Dynamic: provides-extra
Dynamic: requires-dist
Dynamic: requires-python
Dynamic: summary
